<?xml version="1.0" encoding="UTF-8"?>
<qes:espresso xsi:schemaLocation="http://www.quantum-espresso.org/ns/qes/qes-1.0 http://www.quantum-espresso.org/ns/qes/qes_190304.xsd" Units="Hartree atomic units" xmlns:xsi="http://www.w3.org/2001/XMLSchema-instance" xmlns:qes="http://www.quantum-espresso.org/ns/qes/qes-1.0">
  <!--If not explicitely indicated, all quantities are expressed in Hartree atomic units-->
  <general_info>
    <xml_format NAME="QEXSD" VERSION="19.03">QEXSD_19.03</xml_format>
    <creator NAME="PWSCF" VERSION="6.4.1">XML file generated by PWSCF</creator>
    <created DATE="19Aug2023" TIME="22:55:57">This run was terminated on:  22:55:57  19 Aug 2023</created>
    <job></job>
  </general_info>
  <parallel_info>
    <nprocs>1</nprocs>
    <nthreads>1</nthreads>
    <ntasks>1</ntasks>
    <nbgrp>1</nbgrp>
    <npool>1</npool>
    <ndiag>1</ndiag>
  </parallel_info>
  <input>
    <control_variables>
      <title></title>
      <calculation>scf</calculation>
      <restart_mode>from_scratch</restart_mode>
      <prefix>pwscf</prefix>
      <pseudo_dir>.</pseudo_dir>
      <outdir>./</outdir>
      <stress>false</stress>
      <forces>false</forces>
      <wf_collect>true</wf_collect>
      <disk_io>low</disk_io>
      <max_seconds>10000000</max_seconds>
      <nstep>1</nstep>
      <etot_conv_thr>5.000000000000000e-5</etot_conv_thr>
      <forc_conv_thr>5.000000000000000e-4</forc_conv_thr>
      <press_conv_thr>5.000000000000000e-1</press_conv_thr>
      <verbosity>low</verbosity>
      <print_every>100000</print_every>
    </control_variables>
    <atomic_species ntyp="1">
      <species name="C">
        <mass>1.201100000000000e1</mass>
        <pseudo_file>C.pz-vbc.UPF</pseudo_file>
      </species>
    </atomic_species>
    <atomic_structure nat="4" alat="4.661954369829e0" bravais_index="4">
      <atomic_positions>
        <atom name="C" index="1">0.000000000000000e0 0.000000000000000e0 1.230920359808386e1</atom>
        <atom name="C" index="2">0.000000000000000e0 0.000000000000000e0 4.103067866027954e0</atom>
        <atom name="C" index="3">-2.330977184914184e-4 2.691715189401166e0 1.230920359808386e1</atom>
        <atom name="C" index="4">2.331210282632932e0 1.345655726154805e0 4.103067866027954e0</atom>
      </atomic_positions>
      <cell>
        <a1>4.661954369828882e0 0.000000000000000e0 0.000000000000000e0</a1>
        <a2>-2.330977184914441e0 4.037370915555972e0 0.000000000000000e0</a2>
        <a3>0.000000000000000e0 0.000000000000000e0 1.641227146411182e1</a3>
      </cell>
    </atomic_structure>
    <dft>
      <functional>PZ</functional>
    </dft>
    <spin>
      <lsda>false</lsda>
      <noncolin>false</noncolin>
      <spinorbit>false</spinorbit>
    </spin>
    <bands>
      <tot_charge>0.000000000000000e0</tot_charge>
      <occupations>fixed</occupations>
    </bands>
    <basis>
      <gamma_only>false</gamma_only>
      <ecutwfc>1.250000000000000e1</ecutwfc>
      <ecutrho>5.000000000000000e1</ecutrho>
    </basis>
    <electron_control>
      <diagonalization>davidson</diagonalization>
      <mixing_mode>plain</mixing_mode>
      <mixing_beta>7.000000000000000e-1</mixing_beta>
      <conv_thr>5.000000000000000e-7</conv_thr>
      <mixing_ndim>8</mixing_ndim>
      <max_nstep>100</max_nstep>
      <real_space_q>false</real_space_q>
      <real_space_beta>false</real_space_beta>
      <tq_smoothing>false</tq_smoothing>
      <tbeta_smoothing>false</tbeta_smoothing>
      <diago_thr_init>0.000000000000000e0</diago_thr_init>
      <diago_full_acc>false</diago_full_acc>
      <diago_cg_maxiter>20</diago_cg_maxiter>
      <diago_ppcg_maxiter>20</diago_ppcg_maxiter>
      <diago_rmm_ndim>4</diago_rmm_ndim>
      <diago_rmm_conv>false</diago_rmm_conv>
      <diago_gs_nblock>16</diago_gs_nblock>
    </electron_control>
    <k_points_IBZ>
      <monkhorst_pack nk1="4" nk2="4" nk3="4" k1="0" k2="0" k3="0">Monkhorst-Pack</monkhorst_pack>
    </k_points_IBZ>
    <ion_control>
      <ion_dynamics>none</ion_dynamics>
      <upscale>1.000000000000000e2</upscale>
      <remove_rigid_rot>false</remove_rigid_rot>
      <refold_pos>false</refold_pos>
    </ion_control>
    <cell_control>
      <cell_dynamics>none</cell_dynamics>
      <pressure>0.000000000000000e0</pressure>
      <wmass>4.378942716900291e4</wmass>
      <cell_factor>0.000000000000000e0</cell_factor>
      <fix_volume>false</fix_volume>
      <fix_area>false</fix_area>
      <isotropic>false</isotropic>
    </cell_control>
    <symmetry_flags>
      <nosym>false</nosym>
      <nosym_evc>false</nosym_evc>
      <noinv>false</noinv>
      <no_t_rev>false</no_t_rev>
      <force_symmorphic>false</force_symmorphic>
      <use_all_frac>false</use_all_frac>
    </symmetry_flags>
  </input>
  <output>
    <convergence_info>
      <scf_conv>
        <convergence_achieved>false</convergence_achieved>
        <n_scf_steps>4</n_scf_steps>
        <scf_error>9.556318522875040e-7</scf_error>
      </scf_conv>
    </convergence_info>
    <algorithmic_info>
      <real_space_q>false</real_space_q>
      <real_space_beta>false</real_space_beta>
      <uspp>false</uspp>
      <paw>false</paw>
    </algorithmic_info>
    <atomic_species ntyp="1" pseudo_dir=".\">
      <species name="C">
        <mass>1.201100000000000e1</mass>
        <pseudo_file>C.pz-vbc.UPF</pseudo_file>
      </species>
    </atomic_species>
    <atomic_structure nat="4" alat="4.661954369829e0" bravais_index="4">
      <atomic_positions>
        <atom name="C" index="1">0.000000000000000e0 0.000000000000000e0 1.230920359808386e1</atom>
        <atom name="C" index="2">0.000000000000000e0 0.000000000000000e0 4.103067866027954e0</atom>
        <atom name="C" index="3">-2.330977184914184e-4 2.691715189401166e0 1.230920359808386e1</atom>
        <atom name="C" index="4">2.331210282632932e0 1.345655726154805e0 4.103067866027954e0</atom>
      </atomic_positions>
      <cell>
        <a1>4.661954369828882e0 0.000000000000000e0 0.000000000000000e0</a1>
        <a2>-2.330977184914441e0 4.037370915555972e0 0.000000000000000e0</a2>
        <a3>0.000000000000000e0 0.000000000000000e0 1.641227146411182e1</a3>
      </cell>
    </atomic_structure>
    <symmetries>
      <nsym>8</nsym>
      <nrot>24</nrot>
      <space_group>0</space_group>
      <symmetry>
        <info name="identity">crystal_symmetry</info>
        <rotation rank="2" dims="3 3" order="F">
          1.000000000000000e0 0.000000000000000e0 0.000000000000000e0
          0.000000000000000e0 1.000000000000000e0 0.000000000000000e0
          0.000000000000000e0 0.000000000000000e0 1.000000000000000e0
          </rotation>
        <fractional_translation>0.000000000000000e0 0.000000000000000e0 0.000000000000000e0</fractional_translation>
        <equivalent_atoms nat="4" size="4">
          1 2 3 4
          </equivalent_atoms>
      </symmetry>
      <symmetry>
        <info name="180 deg rotation - cart. axis [0,0,1]">crystal_symmetry</info>
        <rotation rank="2" dims="3 3" order="F">
          -1.000000000000000e0 0.000000000000000e0 0.000000000000000e0
          0.000000000000000e0 -1.000000000000000e0 0.000000000000000e0
          0.000000000000000e0 0.000000000000000e0 1.000000000000000e0
          </rotation>
        <fractional_translation>0.000000000000000e0 0.000000000000000e0 4.999999999999999e-1</fractional_translation>
        <equivalent_atoms nat="4" size="4">
          2 1 4 3
          </equivalent_atoms>
      </symmetry>
      <symmetry>
        <info name="180 deg rotation - cryst. axis [1,-1,0]">crystal_symmetry</info>
        <rotation rank="2" dims="3 3" order="F">
          0.000000000000000e0 -1.000000000000000e0 0.000000000000000e0
          -1.000000000000000e0 0.000000000000000e0 0.000000000000000e0
          0.000000000000000e0 0.000000000000000e0 -1.000000000000000e0
          </rotation>
        <fractional_translation>0.000000000000000e0 0.000000000000000e0 4.999999999999998e-1</fractional_translation>
        <equivalent_atoms nat="4" size="4">
          1 2 3 4
          </equivalent_atoms>
      </symmetry>
      <symmetry>
        <info name="180 deg rotation - cryst. axis [1,1,0]">crystal_symmetry</info>
        <rotation rank="2" dims="3 3" order="F">
          0.000000000000000e0 1.000000000000000e0 0.000000000000000e0
          1.000000000000000e0 0.000000000000000e0 0.000000000000000e0
          0.000000000000000e0 0.000000000000000e0 -1.000000000000000e0
          </rotation>
        <fractional_translation>0.000000000000000e0 0.000000000000000e0 0.000000000000000e0</fractional_translation>
        <equivalent_atoms nat="4" size="4">
          2 1 4 3
          </equivalent_atoms>
      </symmetry>
      <symmetry>
        <info name="inversion">crystal_symmetry</info>
        <rotation rank="2" dims="3 3" order="F">
          -1.000000000000000e0 0.000000000000000e0 0.000000000000000e0
          0.000000000000000e0 -1.000000000000000e0 0.000000000000000e0
          0.000000000000000e0 0.000000000000000e0 -1.000000000000000e0
          </rotation>
        <fractional_translation>0.000000000000000e0 0.000000000000000e0 0.000000000000000e0</fractional_translation>
        <equivalent_atoms nat="4" size="4">
          2 1 4 3
          </equivalent_atoms>
      </symmetry>
      <symmetry>
        <info name="inv. 180 deg rotation - cart. axis [0,0,1]">crystal_symmetry</info>
        <rotation rank="2" dims="3 3" order="F">
          1.000000000000000e0 0.000000000000000e0 0.000000000000000e0
          0.000000000000000e0 1.000000000000000e0 0.000000000000000e0
          0.000000000000000e0 0.000000000000000e0 -1.000000000000000e0
          </rotation>
        <fractional_translation>0.000000000000000e0 0.000000000000000e0 4.999999999999998e-1</fractional_translation>
        <equivalent_atoms nat="4" size="4">
          1 2 3 4
          </equivalent_atoms>
      </symmetry>
      <symmetry>
        <info name="inv. 180 deg rotation - cryst. axis [1,-1,0]">crystal_symmetry</info>
        <rotation rank="2" dims="3 3" order="F">
          0.000000000000000e0 1.000000000000000e0 0.000000000000000e0
          1.000000000000000e0 0.000000000000000e0 0.000000000000000e0
          0.000000000000000e0 0.000000000000000e0 1.000000000000000e0
          </rotation>
        <fractional_translation>0.000000000000000e0 0.000000000000000e0 4.999999999999999e-1</fractional_translation>
        <equivalent_atoms nat="4" size="4">
          2 1 4 3
          </equivalent_atoms>
      </symmetry>
      <symmetry>
        <info name="inv. 180 deg rotation - cryst. axis [1,1,0]">crystal_symmetry</info>
        <rotation rank="2" dims="3 3" order="F">
          0.000000000000000e0 -1.000000000000000e0 0.000000000000000e0
          -1.000000000000000e0 0.000000000000000e0 0.000000000000000e0
          0.000000000000000e0 0.000000000000000e0 1.000000000000000e0
          </rotation>
        <fractional_translation>0.000000000000000e0 0.000000000000000e0 0.000000000000000e0</fractional_translation>
        <equivalent_atoms nat="4" size="4">
          1 2 3 4
          </equivalent_atoms>
      </symmetry>
      <symmetry>
        <info name="180 deg rotation - cart. axis [0,1,0]">lattice_symmetry</info>
        <rotation rank="2" dims="3 3" order="F">
          -1.000000000000000e0 1.000000000000000e0 0.000000000000000e0
          0.000000000000000e0 1.000000000000000e0 0.000000000000000e0
          0.000000000000000e0 0.000000000000000e0 -1.000000000000000e0
          </rotation>
      </symmetry>
      <symmetry>
        <info name="180 deg rotation - cryst. axis [2,1,0]">lattice_symmetry</info>
        <rotation rank="2" dims="3 3" order="F">
          1.000000000000000e0 0.000000000000000e0 0.000000000000000e0
          1.000000000000000e0 -1.000000000000000e0 0.000000000000000e0
          0.000000000000000e0 0.000000000000000e0 -1.000000000000000e0
          </rotation>
      </symmetry>
      <symmetry>
        <info name="180 deg rotation - cryst. axis [0,1,0]">lattice_symmetry</info>
        <rotation rank="2" dims="3 3" order="F">
          -1.000000000000000e0 0.000000000000000e0 0.000000000000000e0
          -1.000000000000000e0 1.000000000000000e0 0.000000000000000e0
          0.000000000000000e0 0.000000000000000e0 -1.000000000000000e0
          </rotation>
      </symmetry>
      <symmetry>
        <info name="180 deg rotation - cart. axis [1,0,0]">lattice_symmetry</info>
        <rotation rank="2" dims="3 3" order="F">
          1.000000000000000e0 -1.000000000000000e0 0.000000000000000e0
          0.000000000000000e0 -1.000000000000000e0 0.000000000000000e0
          0.000000000000000e0 0.000000000000000e0 -1.000000000000000e0
          </rotation>
      </symmetry>
      <symmetry>
        <info name=" 60 deg rotation - cryst. axis [0,0,1]">lattice_symmetry</info>
        <rotation rank="2" dims="3 3" order="F">
          1.000000000000000e0 -1.000000000000000e0 0.000000000000000e0
          1.000000000000000e0 0.000000000000000e0 0.000000000000000e0
          0.000000000000000e0 0.000000000000000e0 1.000000000000000e0
          </rotation>
      </symmetry>
      <symmetry>
        <info name=" 60 deg rotation - cryst. axis [0,0,-1]">lattice_symmetry</info>
        <rotation rank="2" dims="3 3" order="F">
          0.000000000000000e0 1.000000000000000e0 0.000000000000000e0
          -1.000000000000000e0 1.000000000000000e0 0.000000000000000e0
          0.000000000000000e0 0.000000000000000e0 1.000000000000000e0
          </rotation>
      </symmetry>
      <symmetry>
        <info name="inv. 180 deg rotation - cart. axis [0,1,0]">lattice_symmetry</info>
        <rotation rank="2" dims="3 3" order="F">
          1.000000000000000e0 -1.000000000000000e0 0.000000000000000e0
          0.000000000000000e0 -1.000000000000000e0 0.000000000000000e0
          0.000000000000000e0 0.000000000000000e0 1.000000000000000e0
          </rotation>
      </symmetry>
      <symmetry>
        <info name="inv. 180 deg rotation - cart. axis [1,0,0]">lattice_symmetry</info>
        <rotation rank="2" dims="3 3" order="F">
          -1.000000000000000e0 1.000000000000000e0 0.000000000000000e0
          0.000000000000000e0 1.000000000000000e0 0.000000000000000e0
          0.000000000000000e0 0.000000000000000e0 1.000000000000000e0
          </rotation>
      </symmetry>
      <symmetry>
        <info name="inv.  60 deg rotation - cryst. axis [0,0,1]">lattice_symmetry</info>
        <rotation rank="2" dims="3 3" order="F">
          -1.000000000000000e0 1.000000000000000e0 0.000000000000000e0
          -1.000000000000000e0 0.000000000000000e0 0.000000000000000e0
          0.000000000000000e0 0.000000000000000e0 -1.000000000000000e0
          </rotation>
      </symmetry>
      <symmetry>
        <info name="inv.  60 deg rotation - cryst. axis [0,0,-1]">lattice_symmetry</info>
        <rotation rank="2" dims="3 3" order="F">
          0.000000000000000e0 -1.000000000000000e0 0.000000000000000e0
          1.000000000000000e0 -1.000000000000000e0 0.000000000000000e0
          0.000000000000000e0 0.000000000000000e0 -1.000000000000000e0
          </rotation>
      </symmetry>
      <symmetry>
        <info name="inv. 120 deg rotation - cryst. axis [0,0,1]">lattice_symmetry</info>
        <rotation rank="2" dims="3 3" order="F">
          0.000000000000000e0 1.000000000000000e0 0.000000000000000e0
          -1.000000000000000e0 1.000000000000000e0 0.000000000000000e0
          0.000000000000000e0 0.000000000000000e0 -1.000000000000000e0
          </rotation>
      </symmetry>
      <symmetry>
        <info name="inv. 120 deg rotation - cryst. axis [0,0,-1]">lattice_symmetry</info>
        <rotation rank="2" dims="3 3" order="F">
          1.000000000000000e0 -1.000000000000000e0 0.000000000000000e0
          1.000000000000000e0 0.000000000000000e0 0.000000000000000e0
          0.000000000000000e0 0.000000000000000e0 -1.000000000000000e0
          </rotation>
      </symmetry>
      <symmetry>
        <info name="120 deg rotation - cryst. axis [0,0,1]">lattice_symmetry</info>
        <rotation rank="2" dims="3 3" order="F">
          0.000000000000000e0 -1.000000000000000e0 0.000000000000000e0
          1.000000000000000e0 -1.000000000000000e0 0.000000000000000e0
          0.000000000000000e0 0.000000000000000e0 1.000000000000000e0
          </rotation>
      </symmetry>
      <symmetry>
        <info name="inv. 180 deg rotation - cryst. axis [2,1,0]">lattice_symmetry</info>
        <rotation rank="2" dims="3 3" order="F">
          -1.000000000000000e0 0.000000000000000e0 0.000000000000000e0
          -1.000000000000000e0 1.000000000000000e0 0.000000000000000e0
          0.000000000000000e0 0.000000000000000e0 1.000000000000000e0
          </rotation>
      </symmetry>
      <symmetry>
        <info name="inv. 180 deg rotation - cryst. axis [0,1,0]">lattice_symmetry</info>
        <rotation rank="2" dims="3 3" order="F">
          1.000000000000000e0 0.000000000000000e0 0.000000000000000e0
          1.000000000000000e0 -1.000000000000000e0 0.000000000000000e0
          0.000000000000000e0 0.000000000000000e0 1.000000000000000e0
          </rotation>
      </symmetry>
      <symmetry>
        <info name="120 deg rotation - cryst. axis [0,0,-1]">lattice_symmetry</info>
        <rotation rank="2" dims="3 3" order="F">
          -1.000000000000000e0 1.000000000000000e0 0.000000000000000e0
          -1.000000000000000e0 0.000000000000000e0 0.000000000000000e0
          0.000000000000000e0 0.000000000000000e0 1.000000000000000e0
          </rotation>
      </symmetry>
    </symmetries>
    <basis_set>
      <gamma_only>false</gamma_only>
      <ecutwfc>1.250000000000000e1</ecutwfc>
      <ecutrho>5.000000000000000e1</ecutrho>
      <fft_grid nr1="15" nr2="15" nr3="54"></fft_grid>
      <fft_smooth nr1="15" nr2="15" nr3="54"></fft_smooth>
      <fft_box nr1="15" nr2="15" nr3="54"></fft_box>
      <ngm>5279</ngm>
      <ngms>5279</ngms>
      <npwx>675</npwx>
      <reciprocal_lattice>
        <b1>1.000000000000000e0 5.773502691895849e-1 0.000000000000000e0</b1>
        <b2>0.000000000000000e0 1.154700538379170e0 0.000000000000000e0</b2>
        <b3>0.000000000000000e0 0.000000000000000e0 2.840529648819804e-1</b3>
      </reciprocal_lattice>
    </basis_set>
    <dft>
      <functional>PZ</functional>
    </dft>
    <magnetization>
      <lsda>false</lsda>
      <noncolin>false</noncolin>
      <spinorbit>false</spinorbit>
      <total>0.000000000000000e0</total>
      <absolute>0.000000000000000e0</absolute>
      <do_magnetization>false</do_magnetization>
    </magnetization>
    <total_energy>
      <etot>-2.241746713355625e1</etot>
      <eband>-2.764018935694708e0</eband>
      <ehart>1.147779912523898e1</ehart>
      <vtxc>-8.993492617857466e0</vtxc>
      <etxc>-6.879024471668592e0</etxc>
      <ewald>-1.028718627154807e1</ewald>
    </total_energy>
    <band_structure>
      <lsda>false</lsda>
      <noncolin>false</noncolin>
      <spinorbit>false</spinorbit>
      <nbnd>8</nbnd>
      <nelec>1.600000000000000e1</nelec>
      <num_of_atomic_wfc>16</num_of_atomic_wfc>
      <wf_collected>true</wf_collected>
      <highestOccupiedLevel>8.598466959981771e-2</highestOccupiedLevel>
      <starting_k_points>
        <monkhorst_pack nk1="4" nk2="4" nk3="4" k1="0" k2="0" k3="0">Monkhorst-Pack</monkhorst_pack>
      </starting_k_points>
      <nks>21</nks>
      <occupations_kind>fixed</occupations_kind>
      <ks_energies>
        <k_point weight="3.125000000000e-2">0.000000000000000e0 0.000000000000000e0 0.000000000000000e0</k_point>
        <npw>675</npw>
        <eigenvalues size="8">
          -5.569221914955619e-1 -5.554642424605434e-1 -1.296720347499330e-1 -1.102258862462694e-1 5.556818009053889e-2
          5.573209990120876e-2 5.695156332850414e-2 5.711152125845963e-2
          </eigenvalues>
        <occupations size="8">
          1.000000000000000e0 1.000000000000000e0 1.000000000000000e0 1.000000000000000e0 1.000000000000000e0
          1.000000000000000e0 1.000000000000000e0 1.000000000000000e0
          </occupations>
      </ks_energies>
      <ks_energies>
        <k_point weight="6.250000000000e-2">0.000000000000000e0 0.000000000000000e0 7.101324122049510e-2</k_point>
        <npw>662</npw>
        <eigenvalues size="8">
          -5.566861830825669e-1 -5.547700230924080e-1 -1.245596217371166e-1 -1.128219307073152e-1 5.588845524057570e-2
          5.605218613645636e-2 5.779601443985831e-2 5.795658434884946e-2
          </eigenvalues>
        <occupations size="8">
          1.000000000000000e0 1.000000000000000e0 1.000000000000000e0 1.000000000000000e0 1.000000000000000e0
          1.000000000000000e0 1.000000000000000e0 1.000000000000000e0
          </occupations>
      </ks_energies>
      <ks_energies>
        <k_point weight="3.125000000000e-2">0.000000000000000e0 0.000000000000000e0 -1.420264824409902e-1</k_point>
        <npw>650</npw>
        <eigenvalues size="8">
          -5.558963492392978e-1 -5.558963417899498e-1 -1.184813710585941e-1 -1.184813624411785e-1 5.908448678295176e-2
          5.908454940965536e-2 5.924606938360312e-2 5.924617145672420e-2
          </eigenvalues>
        <occupations size="8">
          1.000000000000000e0 1.000000000000000e0 1.000000000000000e0 1.000000000000000e0 1.000000000000000e0
          1.000000000000000e0 1.000000000000000e0 1.000000000000000e0
          </occupations>
      </ks_energies>
      <ks_energies>
        <k_point weight="1.250000000000e-1">0.000000000000000e0 2.886751345947924e-1 0.000000000000000e0</k_point>
        <npw>648</npw>
        <eigenvalues size="8">
          -5.011321910270344e-1 -5.003607135453963e-1 -1.117451806877696e-1 -1.098908742576369e-1 -6.140529863092191e-2
          -4.537778200511983e-2 -1.982002063563161e-2 -1.838939026654231e-2
          </eigenvalues>
        <occupations size="8">
          1.000000000000000e0 1.000000000000000e0 1.000000000000000e0 1.000000000000000e0 1.000000000000000e0
          1.000000000000000e0 1.000000000000000e0 1.000000000000000e0
          </occupations>
      </ks_energies>
      <ks_energies>
        <k_point weight="2.500000000000e-1">0.000000000000000e0 2.886751345947924e-1 7.101324122049510e-2</k_point>
        <npw>652</npw>
        <eigenvalues size="8">
          -5.013862405019218e-1 -5.010434403519033e-1 -1.104748443596291e-1 -1.103046998054897e-1 -5.945305719234783e-2
          -4.796661273782582e-2 -1.963510164674634e-2 -1.871614352797828e-2
          </eigenvalues>
        <occupations size="8">
          1.000000000000000e0 1.000000000000000e0 1.000000000000000e0 1.000000000000000e0 1.000000000000000e0
          1.000000000000000e0 1.000000000000000e0 1.000000000000000e0
          </occupations>
      </ks_energies>
      <ks_energies>
        <k_point weight="1.250000000000e-1">0.000000000000000e0 2.886751345947924e-1 -1.420264824409902e-1</k_point>
        <npw>658</npw>
        <eigenvalues size="8">
          -5.014598126859411e-1 -5.014597045818933e-1 -1.102433276678676e-1 -1.102429550199851e-1 -5.413432069680045e-2
          -5.413425838656860e-2 -1.980402021405371e-2 -1.980401637963220e-2
          </eigenvalues>
        <occupations size="8">
          1.000000000000000e0 1.000000000000000e0 1.000000000000000e0 1.000000000000000e0 1.000000000000000e0
          1.000000000000000e0 1.000000000000000e0 1.000000000000000e0
          </occupations>
      </ks_energies>
      <ks_energies>
        <k_point weight="6.250000000000e-2">0.000000000000000e0 -5.773502691895849e-1 0.000000000000000e0</k_point>
        <npw>654</npw>
        <eigenvalues size="8">
          -3.627080630191553e-1 -3.609162524645537e-1 -3.297642021242390e-1 -3.280909854133471e-1 -7.251195266485468e-2
          -6.930307834511630e-2 8.089672115431943e-2 8.593012233905382e-2
          </eigenvalues>
        <occupations size="8">
          1.000000000000000e0 1.000000000000000e0 1.000000000000000e0 1.000000000000000e0 1.000000000000000e0
          1.000000000000000e0 1.000000000000000e0 1.000000000000000e0
          </occupations>
      </ks_energies>
      <ks_energies>
        <k_point weight="1.250000000000e-1">0.000000000000000e0 -5.773502691895849e-1 7.101324122049510e-2</k_point>
        <npw>650</npw>
        <eigenvalues size="8">
          -3.616259902856820e-1 -3.611067913976482e-1 -3.280449082784501e-1 -3.277462016329262e-1 -7.085261257169286e-2
          -6.937678190658039e-2 7.949222541724930e-2 8.364592741036192e-2
          </eigenvalues>
        <occupations size="8">
          1.000000000000000e0 1.000000000000000e0 1.000000000000000e0 1.000000000000000e0 1.000000000000000e0
          1.000000000000000e0 1.000000000000000e0 1.000000000000000e0
          </occupations>
      </ks_energies>
      <ks_energies>
        <k_point weight="6.250000000000e-2">0.000000000000000e0 -5.773502691895849e-1 -1.420264824409902e-1</k_point>
        <npw>664</npw>
        <eigenvalues size="8">
          -3.617749034004140e-1 -3.617748692543656e-1 -3.283534681863775e-1 -3.283534357266842e-1 -7.134410275633272e-2
          -7.134407056030918e-2 8.067140925388863e-2 8.067231343815713e-2
          </eigenvalues>
        <occupations size="8">
          1.000000000000000e0 1.000000000000000e0 1.000000000000000e0 1.000000000000000e0 1.000000000000000e0
          1.000000000000000e0 1.000000000000000e0 1.000000000000000e0
          </occupations>
      </ks_energies>
      <ks_energies>
        <k_point weight="6.250000000000e-2">2.500000000000000e-1 4.330127018921886e-1 0.000000000000000e0</k_point>
        <npw>654</npw>
        <eigenvalues size="8">
          -3.978686320604675e-1 -3.974495122728669e-1 -2.246938196162056e-1 -2.245503475097186e-1 -1.701037615372301e-1
          -1.689333000850347e-1 6.022784856543804e-2 7.318474905386038e-2
          </eigenvalues>
        <occupations size="8">
          1.000000000000000e0 1.000000000000000e0 1.000000000000000e0 1.000000000000000e0 1.000000000000000e0
          1.000000000000000e0 1.000000000000000e0 1.000000000000000e0
          </occupations>
      </ks_energies>
      <ks_energies>
        <k_point weight="1.250000000000e-1">2.500000000000000e-1 4.330127018921886e-1 7.101324122049510e-2</k_point>
        <npw>658</npw>
        <eigenvalues size="8">
          -3.979622224708951e-1 -3.975170533681923e-1 -2.255112420166226e-1 -2.250352141324051e-1 -1.696508516123862e-1
          -1.691879816395613e-1 6.106718378304193e-2 7.046367343853390e-2
          </eigenvalues>
        <occupations size="8">
          1.000000000000000e0 1.000000000000000e0 1.000000000000000e0 1.000000000000000e0 1.000000000000000e0
          1.000000000000000e0 1.000000000000000e0 1.000000000000000e0
          </occupations>
      </ks_energies>
      <ks_energies>
        <k_point weight="6.250000000000e-2">2.500000000000000e-1 4.330127018921886e-1 -1.420264824409902e-1</k_point>
        <npw>642</npw>
        <eigenvalues size="8">
          -3.965583631183050e-1 -3.965583590826740e-1 -2.246050866353131e-1 -2.246050644012599e-1 -1.686969974359509e-1
          -1.686969029165872e-1 6.687641866512708e-2 6.687654731538128e-2
          </eigenvalues>
        <occupations size="8">
          1.000000000000000e0 1.000000000000000e0 1.000000000000000e0 1.000000000000000e0 1.000000000000000e0
          1.000000000000000e0 1.000000000000000e0 1.000000000000000e0
          </occupations>
      </ks_energies>
      <ks_energies>
        <k_point weight="6.250000000000e-2">2.500000000000000e-1 -1.443375672973962e-1 0.000000000000000e0</k_point>
        <npw>648</npw>
        <eigenvalues size="8">
          -5.011330875823521e-1 -5.003618579557942e-1 -1.118052851397590e-1 -1.099497779732789e-1 -6.139999187930526e-2
          -4.537196077591993e-2 -1.974546733723274e-2 -1.831488185702016e-2
          </eigenvalues>
        <occupations size="8">
          1.000000000000000e0 1.000000000000000e0 1.000000000000000e0 1.000000000000000e0 1.000000000000000e0
          1.000000000000000e0 1.000000000000000e0 1.000000000000000e0
          </occupations>
      </ks_energies>
      <ks_energies>
        <k_point weight="1.250000000000e-1">2.500000000000000e-1 -1.443375672973962e-1 -7.101324122049510e-2</k_point>
        <npw>652</npw>
        <eigenvalues size="8">
          -5.013870452392590e-1 -5.010447244801817e-1 -1.105346616663156e-1 -1.103657771186945e-1 -5.944762830707213e-2
          -4.796070040606276e-2 -1.956117003753004e-2 -1.864243054046509e-2
          </eigenvalues>
        <occupations size="8">
          1.000000000000000e0 1.000000000000000e0 1.000000000000000e0 1.000000000000000e0 1.000000000000000e0
          1.000000000000000e0 1.000000000000000e0 1.000000000000000e0
          </occupations>
      </ks_energies>
      <ks_energies>
        <k_point weight="6.250000000000e-2">2.500000000000000e-1 -1.443375672973962e-1 1.420264824409902e-1</k_point>
        <npw>658</npw>
        <eigenvalues size="8">
          -5.014605823489743e-1 -5.014605746998058e-1 -1.103040779097505e-1 -1.103040735956054e-1 -5.412821357280533e-2
          -5.412818872114790e-2 -1.973022622655141e-2 -1.973022122315278e-2
          </eigenvalues>
        <occupations size="8">
          1.000000000000000e0 1.000000000000000e0 1.000000000000000e0 1.000000000000000e0 1.000000000000000e0
          1.000000000000000e0 1.000000000000000e0 1.000000000000000e0
          </occupations>
      </ks_energies>
      <ks_energies>
        <k_point weight="3.125000000000e-2">-5.000000000000000e-1 2.886751345947924e-1 0.000000000000000e0</k_point>
        <npw>654</npw>
        <eigenvalues size="8">
          -3.626823155829635e-1 -3.608877495743685e-1 -3.298316002420200e-1 -3.281535436785564e-1 -7.245366953729260e-2
          -6.924493036716023e-2 8.095222807912952e-2 8.598466959981771e-2
          </eigenvalues>
        <occupations size="8">
          1.000000000000000e0 1.000000000000000e0 1.000000000000000e0 1.000000000000000e0 1.000000000000000e0
          1.000000000000000e0 1.000000000000000e0 1.000000000000000e0
          </occupations>
      </ks_energies>
      <ks_energies>
        <k_point weight="6.250000000000e-2">-5.000000000000000e-1 2.886751345947924e-1 -7.101324122049510e-2</k_point>
        <npw>650</npw>
        <eigenvalues size="8">
          -3.615985329324888e-1 -3.610787636654256e-1 -3.281090320659941e-1 -3.278098596124315e-1 -7.079489197753011e-2
          -6.931918389197913e-2 7.954909181867870e-2 8.369928689102434e-2
          </eigenvalues>
        <occupations size="8">
          1.000000000000000e0 1.000000000000000e0 1.000000000000000e0 1.000000000000000e0 1.000000000000000e0
          1.000000000000000e0 1.000000000000000e0 1.000000000000000e0
          </occupations>
      </ks_energies>
      <ks_energies>
        <k_point weight="3.125000000000e-2">-5.000000000000000e-1 2.886751345947924e-1 1.420264824409902e-1</k_point>
        <npw>664</npw>
        <eigenvalues size="8">
          -3.617470397718524e-1 -3.617470072984740e-1 -3.284172413988913e-1 -3.284172190067843e-1 -7.128603142747661e-2
          -7.128595288743028e-2 8.072676514247890e-2 8.072698428615201e-2
          </eigenvalues>
        <occupations size="8">
          1.000000000000000e0 1.000000000000000e0 1.000000000000000e0 1.000000000000000e0 1.000000000000000e0
          1.000000000000000e0 1.000000000000000e0 1.000000000000000e0
          </occupations>
      </ks_energies>
      <ks_energies>
        <k_point weight="1.250000000000e-1">-2.500000000000000e-1 4.330127018921886e-1 0.000000000000000e0</k_point>
        <npw>654</npw>
        <eigenvalues size="8">
          -3.978698028485601e-1 -3.974507018816685e-1 -2.247454026840159e-1 -2.246045365713388e-1 -1.700452021730914e-1
          -1.688753279734985e-1 6.024750686187152e-2 7.320643025747295e-2
          </eigenvalues>
        <occupations size="8">
          1.000000000000000e0 1.000000000000000e0 1.000000000000000e0 1.000000000000000e0 1.000000000000000e0
          1.000000000000000e0 1.000000000000000e0 1.000000000000000e0
          </occupations>
      </ks_energies>
      <ks_energies>
        <k_point weight="2.500000000000e-1">-2.500000000000000e-1 4.330127018921886e-1 -7.101324122049510e-2</k_point>
        <npw>658</npw>
        <eigenvalues size="8">
          -3.979632194067868e-1 -3.975180556329430e-1 -2.255635928857267e-1 -2.250880154095631e-1 -1.695924636235882e-1
          -1.691297964209250e-1 6.108731551055975e-2 7.048506841868100e-2
          </eigenvalues>
        <occupations size="8">
          1.000000000000000e0 1.000000000000000e0 1.000000000000000e0 1.000000000000000e0 1.000000000000000e0
          1.000000000000000e0 1.000000000000000e0 1.000000000000000e0
          </occupations>
      </ks_energies>
      <ks_energies>
        <k_point weight="1.250000000000e-1">-2.500000000000000e-1 4.330127018921886e-1 1.420264824409902e-1</k_point>
        <npw>642</npw>
        <eigenvalues size="8">
          -3.965592556493053e-1 -3.965592494178487e-1 -2.246580542122629e-1 -2.246579729572628e-1 -1.686391881729408e-1
          -1.686391540953518e-1 6.689736678829633e-2 6.689753869739322e-2
          </eigenvalues>
        <occupations size="8">
          1.000000000000000e0 1.000000000000000e0 1.000000000000000e0 1.000000000000000e0 1.000000000000000e0
          1.000000000000000e0 1.000000000000000e0 1.000000000000000e0
          </occupations>
      </ks_energies>
    </band_structure>
  </output>
  <status>0</status>
  <timing_info>
    <total label="PWSCF">
      <cpu>1.003125000000000e1</cpu>
      <wall>4.522001981735229e0</wall>
    </total>
    <partial label="electrons" calls="1">
      <cpu>8.671875000000000e0</cpu>
      <wall>3.352896928787231e0</wall>
    </partial>
  </timing_info>
  <closed DATE="19 Aug 2023" TIME="22:55:57"></closed>
</qes:espresso>
